CHANGES.txt
INSTALL.txt
LICENSE.txt
MANIFEST.in
Makefile
README.txt
setup.py
Doc/conf.py
Doc/glossary.rst
Doc/index.rst
Doc/includes/__init__.py
Doc/includes/mp_benchmarks.py
Doc/includes/mp_distributing.py
Doc/includes/mp_newtype.py
Doc/includes/mp_pool.py
Doc/includes/mp_synchronize.py
Doc/includes/mp_webserver.py
Doc/includes/mp_workers.py
Doc/library/multiprocessing.rst
Lib/multiprocessing/__init__.py
Lib/multiprocessing/connection.py
Lib/multiprocessing/forking.py
Lib/multiprocessing/heap.py
Lib/multiprocessing/managers.py
Lib/multiprocessing/patch.py
Lib/multiprocessing/pool.py
Lib/multiprocessing/process.py
Lib/multiprocessing/queues.py
Lib/multiprocessing/reduction.py
Lib/multiprocessing/sharedctypes.py
Lib/multiprocessing/synchronize.py
Lib/multiprocessing/tests.py
Lib/multiprocessing/util.py
Lib/multiprocessing/dummy/__init__.py
Lib/multiprocessing/dummy/connection.py
Modules/mmapmodule.c
Modules/_multiprocessing/multiprocessing.c
Modules/_multiprocessing/pipe_connection.c
Modules/_multiprocessing/semaphore.c
Modules/_multiprocessing/socket_connection.c
Modules/_multiprocessing/win32_functions.c
Modules/_multiprocessing/connection.h
Modules/_multiprocessing/multiprocessing.c
Modules/_multiprocessing/multiprocessing.h
Modules/_multiprocessing/pipe_connection.c
Modules/_multiprocessing/semaphore.c
Modules/_multiprocessing/socket_connection.c
Modules/_multiprocessing/win32_functions.c
multiprocessing.egg-info/PKG-INFO
multiprocessing.egg-info/SOURCES.txt
multiprocessing.egg-info/dependency_links.txt
multiprocessing.egg-info/top_level.txt