Metadata-Version: 1.0
Name: multiprocessing
Version: 2.6.2.1
Summary: Backport of the multiprocessing package to Python 2.4 and 2.5
Home-page: http://code.google.com/p/python-multiprocessing
Author: Christian Heimes
Author-email: christian at cheimes dot de
License: BSD Licence
Download-URL: http://pypi.python.org/pypi/multiprocessing
Platform: Unix and Windows
Classifier: Development Status :: 5 - Production/Stable
Classifier: Intended Audience :: Developers
Classifier: Programming Language :: Python
Classifier: Programming Language :: C
Classifier: Operating System :: Microsoft :: Windows
Classifier: Operating System :: POSIX
Classifier: License :: OSI Approved :: BSD License
Classifier: Topic :: Software Development :: Libraries :: Python Modules
